{
  "flags": [
    {
      "id": "timeline-indicator-ref-context-inversion",
      "concern": "Step 5 and Step 12 conflict with the current component ownership: the plan creates `indicatorRef` inside `TimelineEditor.tsx` but then tries to expose it through `useTimelineState`/context so `useExternalDrop` can consume it. In this repo, that context is built above `TimelineEditor`, so the ref cannot be threaded upward as written.",
      "category": "correctness",
      "severity_hint": "likely-significant",
      "evidence": "`src/tools/video-editor/contexts/VideoEditorProvider.tsx` calls `useTimelineState()` and passes its `editor` object into `TimelineEditorContextProvider` before `TimelineEditor.tsx` renders. `src/tools/video-editor/components/TimelineEditor/TimelineEditor.tsx` is a consumer of that context, not an owner of it. The updated plan's Step 5 creates `indicatorRef` in `TimelineEditorComponent`, while Step 12 says to add `indicatorRef` to context so `useClipDrag` and `useExternalDrop` can access it. That is a child-to-parent dependency inversion in the current architecture."
    }
  ],
  "verified_flag_ids": [
    "timeline-indicator-rerender-loop",
    "timeline-new-track-affordance-still-split",
    "timeline-onchange-ownership-misread",
    "plan-review-1",
    "plan-review-2",
    "plan-review-3"
  ],
  "disputed_flag_ids": []
}
